llm_terminal/__init__.py
llm_terminal/app.py
llm_terminal-0.1.0.dist-info/METADATA
llm_terminal-0.1.0.dist-info/WHEEL
llm_terminal-0.1.0.dist-info/entry_points.txt
llm_terminal-0.1.0.dist-info/RECORD
