Metadata-Version: 2.4
Name: llm_terminal
Version: 0.1.0
Summary: A terminal-based UI for LLMs with PydanticAI and MCP integration
Author-email: Ferdous <ferdous@hey.com>
License: MIT
Requires-Python: >=3.10
Requires-Dist: ipykernel>=6.29.5
Requires-Dist: openai
Requires-Dist: pydantic-ai-slim[mcp,openai]
Requires-Dist: ruff
Requires-Dist: textual
Requires-Dist: twine>=6.1.0
